dyv
odooast
