Metadata-Version: 1.0
Name: dyv
Version: 0.5.1
Summary: dyv
Home-page: https://example.org
Author: me
Author-email: me@example.org
License: LGPL v3
Keywords: dyv
Platform: UNKNOWN
